preserves/__init__.py
preserves/binary.py
preserves/compare.py
preserves/compat.py
preserves/error.py
preserves/fold.py
preserves/merge.py
preserves/path.prb
preserves/path.py
preserves/schema.prb
preserves/schema.py
preserves/text.py
preserves/values.py
preserves-0.996.3.dist-info/METADATA
preserves-0.996.3.dist-info/WHEEL
preserves-0.996.3.dist-info/top_level.txt
preserves-0.996.3.dist-info/RECORD
