Metadata-Version: 2.4
Name: preserves
Version: 0.996.3
Summary: Data serialization format
Author-email: Tony Garnock-Jones <tonyg@leastfixedpoint.com>
License: Apache-2.0
Project-URL: Homepage, https://preserves.dev/
Project-URL: Issues, https://gitlab.com/preserves/preserves/-/issues
Classifier: Development Status :: 4 - Beta
Classifier: Intended Audience :: Developers
Classifier: Topic :: Software Development :: Libraries :: Python Modules
Classifier: License :: OSI Approved :: Apache Software License
Classifier: Programming Language :: Python :: 3
Requires-Python: <4,>=3.6
Provides-Extra: dev
Requires-Dist: build; extra == "dev"
Requires-Dist: coverage; extra == "dev"
Requires-Dist: mkdocs; extra == "dev"
Requires-Dist: mkdocstrings[python]; extra == "dev"
Requires-Dist: mkdocs-material; extra == "dev"
Requires-Dist: mkdocs-macros-plugin; extra == "dev"
Requires-Dist: mkdocs-git-revision-date-localized-plugin; extra == "dev"
Requires-Dist: twine; extra == "dev"
